<mbm>
  <entry id="0">
    <source>〉 You have found the demon in{F801}question...{F801}{F802}〉 The demon seems to have lost its{F801}mind. The only way to stop it is to{F801}defeat it and hope it calms down.{F801}</source>
    <target>〉 You have found the demon in{F801}question...{F801}{F802}〉 The demon seems to have lost its{F801}mind. The only way to stop it is to{F801}defeat it and hope it calms down.{F801}</target>
  </entry>
  <entry id="1">
    <source>〉 The demon runs away...{F801}</source>
    <target>〉 The demon runs away...{F801}</target>
  </entry>
</mbm>