<mbm>
  <entry id="0">
    <source>I would like to ask a child of man to slay a{F801}certain being for me. Its name is {F804,5}{F873,1},{F804,0}{F801}an entity that broke away from God to become{F801}the ruler of the silent world. I will use my{F801}powers to link the {F804,5}Sky Tower{F804,0} to its home{F801}dimension temporarily. Please come to my aid.{F801}</source>
    <target>I would like to ask a child of man to slay a{F801}certain being for me. Its name is {F804,5}{F873,1},{F804,0}{F801}an entity that broke away from God to become{F801}the ruler of the silent world. I will use my{F801}powers to link the {F804,5}Sky Tower{F804,0} to its home{F801}dimension temporarily. Please come to my aid.{F801}</target>
  </entry>
  <entry id="1">
    <source>Delivery quest description template second time{F801}Clear conditions:{F801}Bring {F878,1} {F872,1}s{F801}Bring {F878,2} {F872,2}s{F801}Bring {F878,3} {F872,3}s{F801}Reard:{F801}{F878,4} {F872,4}s{F801}</source>
    <target>Delivery quest description template second time{F801}Clear conditions:{F801}Bring {F878,1} {F872,1}s{F801}Bring {F878,2} {F872,2}s{F801}Bring {F878,3} {F872,3}s{F801}Reard:{F801}{F878,4} {F872,4}s{F801}</target>
  </entry>
</mbm>